asynmsg.py
asynmsg-0.2.4.dist-info/DESCRIPTION.rst
asynmsg-0.2.4.dist-info/METADATA
asynmsg-0.2.4.dist-info/RECORD
asynmsg-0.2.4.dist-info/WHEEL
asynmsg-0.2.4.dist-info/metadata.json
asynmsg-0.2.4.dist-info/top_level.txt
