Metadata-Version: 2.0
Name: asynmsg
Version: 0.2.4
Summary: A library help to build tcp server/client application
Home-page: https://github.com/sunjinopensource/asynmsg/
Author: Sun Jin
Author-email: sunjinopensource@qq.com
License: UNKNOWN
Platform: UNKNOWN
Classifier: Development Status :: 3 - Alpha
Classifier: Intended Audience :: Developers
Classifier: License :: OSI Approved :: MIT License
Classifier: Operating System :: OS Independent
Classifier: Programming Language :: Python
Classifier: Programming Language :: Python :: 3
